setup.py
stormed/__init__.py
stormed/channel.py
stormed/connection.py
stormed/frame.py
stormed/heartbeat.py
stormed/message.py
stormed/serialization.py
stormed/util.py
stormed/version.py
stormed/method/__init__.py
stormed/method/basic.py
stormed/method/channel.py
stormed/method/connection.py
stormed/method/constant.py
stormed/method/exchange.py
stormed/method/queue.py
stormed/method/tx.py
stormed/method/codegen/__init__.py
stormed/method/codegen/access.py
stormed/method/codegen/basic.py
stormed/method/codegen/channel.py
stormed/method/codegen/connection.py
stormed/method/codegen/exchange.py
stormed/method/codegen/queue.py
stormed/method/codegen/tx.py
test/test_channel.py
test/test_connection.py
test/test_serialization.py
toamqp.egg-info/PKG-INFO
toamqp.egg-info/SOURCES.txt
toamqp.egg-info/dependency_links.txt
toamqp.egg-info/requires.txt
toamqp.egg-info/top_level.txt