Metadata-Version: 1.0
Name: toamqp
Version: 0.2.3
Summary: native tornadoweb amqp 0-9-1 client implementation. Forked From https://github.com/paolo-losi/stormed-amqp/
Home-page: http://github.com/bufferx/stormed-amqp/
Author: ZY ZHANG
Author-email: idup2x@gmail.com
License: http://www.opensource.org/licenses/mit-license.html
Keywords: tornado,mq,rabbitmq,amqp,tornado amqp,tornado,rabbitmq
Platform: UNKNOWN
